mkdocs_build_cache/__init__.py
mkdocs_build_cache/plugin.py
mkdocs_build_cache_plugin-0.1.0.dist-info/LICENSE
mkdocs_build_cache_plugin-0.1.0.dist-info/METADATA
mkdocs_build_cache_plugin-0.1.0.dist-info/WHEEL
mkdocs_build_cache_plugin-0.1.0.dist-info/entry_points.txt
mkdocs_build_cache_plugin-0.1.0.dist-info/top_level.txt
mkdocs_build_cache_plugin-0.1.0.dist-info/RECORD
