Metadata-Version: 2.2
Name: mkdocs_build_cache_plugin
Version: 0.1.0
Summary: MkDocs plugin to check if a build is necessary by hashing configuration and documentation files.
Author-email: kmaliszewski <kmaliszewski.dev@gmail.com>
License: MIT
Project-URL: Homepage, https://github.com/mrzysztof/mkdocs-build-cache-plugin
Project-URL: Issues, https://github.com/mrzysztof/mkdocs-build-cache-plugin/issues
Classifier: Programming Language :: Python :: 3
Classifier: Operating System :: OS Independent
Requires-Python: >=3.8
License-File: LICENSE
